{
  "$schema": "../schemas/participants.schema.json",
  "participants": [
    {
      "participant_id": "P1",
      "age": 63,
      "gender": "male",
      "handedness": "unknown",
      "vision": "glasses",
      "experience_years": 40,
      "programming_languages": [
        "CoffeeScript JavaScript Python Pascal C",
        "C++ Fortran Algol PHP"
      ]
    },
    {
      "participant_id": "P2",
      "age": 24,
      "gender": "male",
      "handedness": "unknown",
      "vision": "glasses",
      "experience_years": 5,
      "programming_languages": [
        "c++",
        "php",
        "delphi"
      ]
    },
    {
      "participant_id": "P3",
      "age": 27,
      "gender": "female",
      "handedness": "unknown",
      "vision": "none",
      "experience_years": 0,
      "programming_languages": [
        "c#"
      ]
    },
    {
      "participant_id": "P4",
      "age": 24,
      "gender": "male",
      "handedness": "unknown",
      "vision": "glasses",
      "experience_years": 10,
      "programming_languages": [
        "Python C++ C HTML/PHP/SQL"
      ]
    },
    {
      "participant_id": "P5",
      "age": 24,
      "gender": "male",
      "handedness": "unknown",
      "vision": "none",
      "experience_years": 5,
      "programming_languages": [
        "objective C",
        "C"
      ]
    },
    {
      "participant_id": "P6",
      "age": 21,
      "gender": "male",
      "handedness": "unknown",
      "vision": "none",
      "experience_years": 3,
      "programming_languages": [
        "C C++ SQL"
      ]
    },
    {
      "participant_id": "P7",
      "age": 19,
      "gender": "male",
      "handedness": "unknown",
      "vision": "none",
      "experience_years": 0,
      "programming_languages": []
    },
    {
      "participant_id": "P8",
      "age": 26,
      "gender": "female",
      "handedness": "unknown",
      "vision": "none",
      "experience_years": 1,
      "programming_languages": [
        "C++"
      ]
    },
    {
      "participant_id": "P9",
      "age": 38,
      "gender": "male",
      "handedness": "unknown",
      "vision": "none",
      "experience_years": 14,
      "programming_languages": [
        "c++ high python low bash high haskell low assembler low java script medium"
      ]
    },
    {
      "participant_id": "P10",
      "age": 32,
      "gender": "male",
      "handedness": "unknown",
      "vision": "none",
      "experience_years": 5,
      "programming_languages": [
        "C",
        "C++",
        "Pascal",
        "Delphi"
      ]
    },
    {
      "participant_id": "P11",
      "age": 34,
      "gender": "male",
      "handedness": "unknown",
      "vision": "glasses",
      "experience_years": 16,
      "programming_languages": [
        "PHP Python Ruby Assembly C++ JavaScript"
      ]
    },
    {
      "participant_id": "P12",
      "age": 44,
      "gender": "female",
      "handedness": "unknown",
      "vision": "none",
      "experience_years": 4,
      "programming_languages": [
        "python C++"
      ]
    },
    {
      "participant_id": "P13",
      "age": 28,
      "gender": "female",
      "handedness": "unknown",
      "vision": "contact_lenses",
      "experience_years": 7,
      "programming_languages": [
        "rhinoscript",
        "python"
      ]
    },
    {
      "participant_id": "P14",
      "age": 24,
      "gender": "male",
      "handedness": "unknown",
      "vision": "none",
      "experience_years": 5,
      "programming_languages": [
        "Python",
        "C++",
        "C#",
        "HTML",
        "PHP",
        "Shell"
      ]
    },
    {
      "participant_id": "P15",
      "age": 32,
      "gender": "male",
      "handedness": "unknown",
      "vision": "none",
      "experience_years": 2,
      "programming_languages": [
        "Javascript",
        "C",
        "MelScript"
      ]
    },
    {
      "participant_id": "P16",
      "age": 28,
      "gender": "male",
      "handedness": "unknown",
      "vision": "none",
      "experience_years": 5,
      "programming_languages": [
        "C",
        "C++",
        "C#",
        "C#.net",
        "ASP",
        "ASP.net",
        "HTML"
      ]
    },
    {
      "participant_id": "P17",
      "age": 27,
      "gender": "male",
      "handedness": "unknown",
      "vision": "none",
      "experience_years": 2,
      "programming_languages": [
        "Python",
        "C#",
        "JavaScript"
      ]
    },
    {
      "participant_id": "P18",
      "age": 22,
      "gender": "female",
      "handedness": "unknown",
      "vision": "glasses",
      "experience_years": 4,
      "programming_languages": [
        "Currently learning Lisp: low",
        "C/C++: low",
        "MySQL: low-medium",
        "HTML/CSS: medium",
        "Javascript: low-medium"
      ]
    },
    {
      "participant_id": "P19",
      "age": 20,
      "gender": "female",
      "handedness": "unknown",
      "vision": "none",
      "experience_years": 3,
      "programming_languages": [
        "c/c++"
      ]
    },
    {
      "participant_id": "P20",
      "age": 19,
      "gender": "male",
      "handedness": "unknown",
      "vision": "none",
      "experience_years": 2,
      "programming_languages": [
        "Pascal Assembly C Java Javascripit"
      ]
    },
    {
      "participant_id": "P21",
      "age": 21,
      "gender": "male",
      "handedness": "unknown",
      "vision": "none",
      "experience_years": 3,
      "programming_languages": [
        "C",
        "JavaScript"
      ]
    },
    {
      "participant_id": "P22",
      "age": 21,
      "gender": "male",
      "handedness": "unknown",
      "vision": "none",
      "experience_years": 2,
      "programming_languages": [
        "C",
        "PHP",
        "SQL",
        "Phyton"
      ]
    },
    {
      "participant_id": "P23",
      "age": 20,
      "gender": "male",
      "handedness": "unknown",
      "vision": "glasses",
      "experience_years": 4,
      "programming_languages": [
        "C++ low C# low R medium SAS medium Matlab medium Java low"
      ]
    },
    {
      "participant_id": "P24",
      "age": 20,
      "gender": "male",
      "handedness": "unknown",
      "vision": "none",
      "experience_years": 6,
      "programming_languages": [
        "C"
      ]
    },
    {
      "participant_id": "P25",
      "age": 19,
      "gender": "male",
      "handedness": "unknown",
      "vision": "none",
      "experience_years": 3,
      "programming_languages": [
        "C javascript"
      ]
    },
    {
      "participant_id": "P26",
      "age": 24,
      "gender": "male",
      "handedness": "unknown",
      "vision": "none",
      "experience_years": 7,
      "programming_languages": [
        "C/C++",
        "C#",
        "Javascript"
      ]
    },
    {
      "participant_id": "P27",
      "age": 31,
      "gender": "male",
      "handedness": "unknown",
      "vision": "glasses",
      "experience_years": 2,
      "programming_languages": [
        "javascript",
        "C",
        "Python"
      ]
    },
    {
      "participant_id": "P28",
      "age": 25,
      "gender": "male",
      "handedness": "unknown",
      "vision": "none",
      "experience_years": 5,
      "programming_languages": [
        "c c#"
      ]
    },
    {
      "participant_id": "P29",
      "age": 22,
      "gender": "male",
      "handedness": "unknown",
      "vision": "contact_lenses",
      "experience_years": 2,
      "programming_languages": [
        "c low c++ low java low"
      ]
    },
    {
      "participant_id": "P30",
      "age": 24,
      "gender": "male",
      "handedness": "unknown",
      "vision": "none",
      "experience_years": 0,
      "programming_languages": [
        "low"
      ]
    },
    {
      "participant_id": "P31",
      "age": 23,
      "gender": "male",
      "handedness": "unknown",
      "vision": "none",
      "experience_years": 5,
      "programming_languages": [
        "c",
        "php"
      ]
    },
    {
      "participant_id": "P32",
      "age": 25,
      "gender": "male",
      "handedness": "unknown",
      "vision": "glasses",
      "experience_years": 8,
      "programming_languages": [
        "php sql html"
      ]
    },
    {
      "participant_id": "P33",
      "age": 23,
      "gender": "male",
      "handedness": "unknown",
      "vision": "none",
      "experience_years": 9,
      "programming_languages": [
        "C#",
        "Python",
        "C",
        "php"
      ]
    },
    {
      "participant_id": "P34",
      "age": 26,
      "gender": "male",
      "handedness": "unknown",
      "vision": "none",
      "experience_years": 10,
      "programming_languages": [
        "C C# SQL"
      ]
    },
    {
      "participant_id": "P35",
      "age": 20,
      "gender": "male",
      "handedness": "unknown",
      "vision": "contact_lenses",
      "experience_years": 3,
      "programming_languages": [
        "C Delphi Java"
      ]
    },
    {
      "participant_id": "P36",
      "age": 20,
      "gender": "female",
      "handedness": "unknown",
      "vision": "none",
      "experience_years": 0,
      "programming_languages": []
    },
    {
      "participant_id": "P37",
      "age": 18,
      "gender": "male",
      "handedness": "unknown",
      "vision": "none",
      "experience_years": 0,
      "programming_languages": [
        "HTML - low",
        "Bash - low"
      ]
    },
    {
      "participant_id": "P38",
      "age": 19,
      "gender": "male",
      "handedness": "unknown",
      "vision": "glasses",
      "experience_years": 0,
      "programming_languages": []
    },
    {
      "participant_id": "P39",
      "age": 68,
      "gender": "female",
      "handedness": "unknown",
      "vision": "glasses",
      "experience_years": 5,
      "programming_languages": [
        "javascript"
      ]
    },
    {
      "participant_id": "P40",
      "age": 21,
      "gender": "male",
      "handedness": "unknown",
      "vision": "glasses",
      "experience_years": 2,
      "programming_languages": [
        "C C++ Java Python MySQL T-SQL Lisp Prolog PHP HTML JavaScript"
      ]
    },
    {
      "participant_id": "P41",
      "age": 22,
      "gender": "male",
      "handedness": "unknown",
      "vision": "glasses",
      "experience_years": 6,
      "programming_languages": [
        "C# ruby"
      ]
    },
    {
      "participant_id": "P42",
      "age": 27,
      "gender": "male",
      "handedness": "unknown",
      "vision": "glasses",
      "experience_years": 5,
      "programming_languages": [
        "Python C Java"
      ]
    },
    {
      "participant_id": "P43",
      "age": 26,
      "gender": "male",
      "handedness": "unknown",
      "vision": "none",
      "experience_years": 2,
      "programming_languages": [
        "c",
        "c#",
        "assebler"
      ]
    },
    {
      "participant_id": "P44",
      "age": 21,
      "gender": "male",
      "handedness": "unknown",
      "vision": "none",
      "experience_years": 2,
      "programming_languages": [
        "C# C Pascal"
      ]
    },
    {
      "participant_id": "P45",
      "age": 20,
      "gender": "male",
      "handedness": "unknown",
      "vision": "none",
      "experience_years": 1,
      "programming_languages": [
        "I coded with Java a few years back",
        "and now I am starting to grasp Scala."
      ]
    },
    {
      "participant_id": "P46",
      "age": 25,
      "gender": "male",
      "handedness": "unknown",
      "vision": "none",
      "experience_years": 7,
      "programming_languages": [
        "R C SAS PHP"
      ]
    },
    {
      "participant_id": "P47",
      "age": 32,
      "gender": "male",
      "handedness": "unknown",
      "vision": "none",
      "experience_years": 20,
      "programming_languages": [
        "Basic - low C - medium Java - low Python - medium Scala - low x87 & Atmel AVR assembly - low"
      ]
    },
    {
      "participant_id": "P48",
      "age": 38,
      "gender": "male",
      "handedness": "unknown",
      "vision": "none",
      "experience_years": 15,
      "programming_languages": [
        "C",
        "C++",
        "MATLAB",
        "Pascal",
        "Modula-2",
        "C#"
      ]
    },
    {
      "participant_id": "P49",
      "age": 21,
      "gender": "male",
      "handedness": "unknown",
      "vision": "none",
      "experience_years": 3,
      "programming_languages": [
        "Java C Scala"
      ]
    },
    {
      "participant_id": "P50",
      "age": 22,
      "gender": "male",
      "handedness": "unknown",
      "vision": "glasses",
      "experience_years": 0,
      "programming_languages": [
        "C - low"
      ]
    },
    {
      "participant_id": "P51",
      "age": 38,
      "gender": "male",
      "handedness": "unknown",
      "vision": "glasses",
      "experience_years": 10,
      "programming_languages": [
        "c++ python matlab sql assembler javascript c#"
      ]
    },
    {
      "participant_id": "P52",
      "age": 23,
      "gender": "male",
      "handedness": "unknown",
      "vision": "none",
      "experience_years": 5,
      "programming_languages": [
        "Php Java Scala"
      ]
    },
    {
      "participant_id": "P53",
      "age": 19,
      "gender": "male",
      "handedness": "unknown",
      "vision": "none",
      "experience_years": 10,
      "programming_languages": [
        "PHP",
        "Python",
        "GML",
        "Scala",
        "VB.NET"
      ]
    },
    {
      "participant_id": "P54",
      "age": 22,
      "gender": "male",
      "handedness": "unknown",
      "vision": "none",
      "experience_years": 4,
      "programming_languages": [
        "Python",
        "C",
        "Javascript",
        "HTML",
        "Lisp",
        "Prolog"
      ]
    },
    {
      "participant_id": "P55",
      "age": 19,
      "gender": "male",
      "handedness": "unknown",
      "vision": "none",
      "experience_years": 7,
      "programming_languages": [
        "C",
        "Pascal",
        "Delphi",
        "Java"
      ]
    },
    {
      "participant_id": "P56",
      "age": 20,
      "gender": "male",
      "handedness": "unknown",
      "vision": "glasses",
      "experience_years": 3,
      "programming_languages": [
        "C",
        "C#",
        "php",
        "javascript",
        "shell"
      ]
    },
    {
      "participant_id": "P57",
      "age": 19,
      "gender": "male",
      "handedness": "unknown",
      "vision": "glasses",
      "experience_years": 4,
      "programming_languages": [
        "Java",
        "HTML",
        "CSS",
        "Apex",
        "PHP",
        "Javascript",
        "C#",
        "ASP.NET"
      ]
    },
    {
      "participant_id": "P58",
      "age": 21,
      "gender": "male",
      "handedness": "unknown",
      "vision": "none",
      "experience_years": 2,
      "programming_languages": [
        "C#",
        "html",
        "Python",
        "CSS",
        "Javascript",
        "Java"
      ]
    },
    {
      "participant_id": "P59",
      "age": 26,
      "gender": "female",
      "handedness": "unknown",
      "vision": "none",
      "experience_years": 3,
      "programming_languages": [
        "c# C++ python c r"
      ]
    },
    {
      "participant_id": "P60",
      "age": 20,
      "gender": "male",
      "handedness": "unknown",
      "vision": "none",
      "experience_years": 4,
      "programming_languages": [
        "Visual Basic Pascal C"
      ]
    },
    {
      "participant_id": "P61",
      "age": 21,
      "gender": "male",
      "handedness": "unknown",
      "vision": "none",
      "experience_years": 3,
      "programming_languages": [
        "C",
        "Javascript"
      ]
    },
    {
      "participant_id": "P62",
      "age": 20,
      "gender": "male",
      "handedness": "unknown",
      "vision": "glasses",
      "experience_years": 3,
      "programming_languages": [
        "Java"
      ]
    },
    {
      "participant_id": "P63",
      "age": 31,
      "gender": "male",
      "handedness": "unknown",
      "vision": "none",
      "experience_years": 8,
      "programming_languages": [
        "Python",
        "C"
      ]
    },
    {
      "participant_id": "P64",
      "age": 22,
      "gender": "male",
      "handedness": "unknown",
      "vision": "glasses",
      "experience_years": 5,
      "programming_languages": [
        "C",
        "Handel-C",
        "VHDL",
        "C++"
      ]
    },
    {
      "participant_id": "P65",
      "age": 24,
      "gender": "female",
      "handedness": "unknown",
      "vision": "none",
      "experience_years": 1,
      "programming_languages": [
        "html"
      ]
    },
    {
      "participant_id": "P66",
      "age": 25,
      "gender": "female",
      "handedness": "unknown",
      "vision": "none",
      "experience_years": 6,
      "programming_languages": [
        "Ruby R"
      ]
    },
    {
      "participant_id": "P67",
      "age": 35,
      "gender": "male",
      "handedness": "unknown",
      "vision": "glasses",
      "experience_years": 23,
      "programming_languages": [
        "C/C++",
        "Python"
      ]
    },
    {
      "participant_id": "P68",
      "age": 20,
      "gender": "male",
      "handedness": "unknown",
      "vision": "none",
      "experience_years": 1,
      "programming_languages": [
        "asmpley"
      ]
    },
    {
      "participant_id": "P69",
      "age": 31,
      "gender": "male",
      "handedness": "unknown",
      "vision": "none",
      "experience_years": 5,
      "programming_languages": [
        "C++"
      ]
    },
    {
      "participant_id": "P70",
      "age": 23,
      "gender": "male",
      "handedness": "unknown",
      "vision": "glasses",
      "experience_years": 2,
      "programming_languages": [
        "C Javascript"
      ]
    },
    {
      "participant_id": "P71",
      "age": 21,
      "gender": "male",
      "handedness": "unknown",
      "vision": "glasses",
      "experience_years": 1,
      "programming_languages": [
        "java",
        "c"
      ]
    },
    {
      "participant_id": "P72",
      "age": 24,
      "gender": "male",
      "handedness": "unknown",
      "vision": "none",
      "experience_years": 1,
      "programming_languages": [
        "c++ java PHP mysql html"
      ]
    },
    {
      "participant_id": "P73",
      "age": 24,
      "gender": "male",
      "handedness": "unknown",
      "vision": "none",
      "experience_years": 8,
      "programming_languages": [
        "C - low Python - medium"
      ]
    },
    {
      "participant_id": "P74",
      "age": 27,
      "gender": "male",
      "handedness": "unknown",
      "vision": "glasses",
      "experience_years": 16,
      "programming_languages": [
        "C++ high C# high Lisp low Prolog low"
      ]
    },
    {
      "participant_id": "P75",
      "age": 27,
      "gender": "male",
      "handedness": "unknown",
      "vision": "none",
      "experience_years": 1,
      "programming_languages": [
        "C Python Java"
      ]
    },
    {
      "participant_id": "P76",
      "age": 23,
      "gender": "female",
      "handedness": "unknown",
      "vision": "glasses",
      "experience_years": 4,
      "programming_languages": [
        "C# C C++",
        "Java"
      ]
    },
    {
      "participant_id": "P77",
      "age": 20,
      "gender": "male",
      "handedness": "unknown",
      "vision": "none",
      "experience_years": 3,
      "programming_languages": [
        "Pascal",
        "Delphi",
        "C - medium"
      ]
    },
    {
      "participant_id": "P78",
      "age": 22,
      "gender": "male",
      "handedness": "unknown",
      "vision": "none",
      "experience_years": 0,
      "programming_languages": [
        "c language"
      ]
    },
    {
      "participant_id": "P79",
      "age": 22,
      "gender": "male",
      "handedness": "unknown",
      "vision": "none",
      "experience_years": 8,
      "programming_languages": [
        "php",
        "javascript",
        "python",
        "c"
      ]
    },
    {
      "participant_id": "P80",
      "age": 32,
      "gender": "male",
      "handedness": "unknown",
      "vision": "contact_lenses",
      "experience_years": 25,
      "programming_languages": [
        "BASIC - medium Ruby - m Python - m Pascal - m Scala - m Kotlin - l Java - h Perl - m and so on."
      ]
    },
    {
      "participant_id": "P81",
      "age": 22,
      "gender": "male",
      "handedness": "unknown",
      "vision": "glasses",
      "experience_years": 1,
      "programming_languages": [
        "Java C"
      ]
    },
    {
      "participant_id": "P82",
      "age": 23,
      "gender": "male",
      "handedness": "unknown",
      "vision": "none",
      "experience_years": 9,
      "programming_languages": [
        "Python",
        "C++",
        "VHDL",
        "matlab",
        "Bash"
      ]
    },
    {
      "participant_id": "P83",
      "age": 19,
      "gender": "male",
      "handedness": "unknown",
      "vision": "none",
      "experience_years": 5,
      "programming_languages": [
        "Python",
        "Java"
      ]
    },
    {
      "participant_id": "P84",
      "age": 30,
      "gender": "male",
      "handedness": "unknown",
      "vision": "glasses",
      "experience_years": 5,
      "programming_languages": [
        "C medium C++ medium Java medium C# low bash medium"
      ]
    },
    {
      "participant_id": "P85",
      "age": 25,
      "gender": "male",
      "handedness": "unknown",
      "vision": "glasses",
      "experience_years": 6,
      "programming_languages": [
        "Scala",
        "C",
        "C++",
        "C#",
        "Javascript"
      ]
    },
    {
      "participant_id": "P86",
      "age": 24,
      "gender": "female",
      "handedness": "unknown",
      "vision": "none",
      "experience_years": 5,
      "programming_languages": [
        "c#",
        "javascript",
        "ruby"
      ]
    },
    {
      "participant_id": "P87",
      "age": 29,
      "gender": "male",
      "handedness": "unknown",
      "vision": "none",
      "experience_years": 20,
      "programming_languages": [
        "Python Ruby C#"
      ]
    },
    {
      "participant_id": "P88",
      "age": 28,
      "gender": "male",
      "handedness": "unknown",
      "vision": "glasses",
      "experience_years": 4,
      "programming_languages": [
        "c# medium java high c medium c++ low javascript medium"
      ]
    },
    {
      "participant_id": "P89",
      "age": 21,
      "gender": "male",
      "handedness": "unknown",
      "vision": "none",
      "experience_years": 3,
      "programming_languages": [
        "C",
        "Java",
        "C++",
        "C#"
      ]
    },
    {
      "participant_id": "P90",
      "age": 28,
      "gender": "male",
      "handedness": "unknown",
      "vision": "glasses",
      "experience_years": 0,
      "programming_languages": [
        "Visual Basic"
      ]
    },
    {
      "participant_id": "P91",
      "age": 21,
      "gender": "male",
      "handedness": "unknown",
      "vision": "none",
      "experience_years": 6,
      "programming_languages": [
        "C# Java C Javascript"
      ]
    },
    {
      "participant_id": "P92",
      "age": 47,
      "gender": "male",
      "handedness": "unknown",
      "vision": "glasses",
      "experience_years": 37,
      "programming_languages": [
        "C - High Assembly - High Cobol - Medium Bash/Unix Shell - High PHP - High"
      ]
    },
    {
      "participant_id": "P93",
      "age": 25,
      "gender": "female",
      "handedness": "unknown",
      "vision": "none",
      "experience_years": 0,
      "programming_languages": [
        "I know of Python but none."
      ]
    },
    {
      "participant_id": "P94",
      "age": 27,
      "gender": "male",
      "handedness": "unknown",
      "vision": "none",
      "experience_years": 5,
      "programming_languages": [
        "Matlab.C++"
      ]
    },
    {
      "participant_id": "P95",
      "age": 25,
      "gender": "female",
      "handedness": "unknown",
      "vision": "glasses",
      "experience_years": 5,
      "programming_languages": [
        "c c++ vb"
      ]
    },
    {
      "participant_id": "P96",
      "age": 20,
      "gender": "male",
      "handedness": "unknown",
      "vision": "none",
      "experience_years": 2,
      "programming_languages": [
        "C Python Javascript/PHP"
      ]
    },
    {
      "participant_id": "P97",
      "age": 22,
      "gender": "male",
      "handedness": "unknown",
      "vision": "none",
      "experience_years": 3,
      "programming_languages": [
        "c c++ my sql java"
      ]
    },
    {
      "participant_id": "P98",
      "age": 25,
      "gender": "male",
      "handedness": "unknown",
      "vision": "glasses",
      "experience_years": 3,
      "programming_languages": [
        "Python",
        "Javascript",
        "C"
      ]
    },
    {
      "participant_id": "P99",
      "age": 34,
      "gender": "male",
      "handedness": "unknown",
      "vision": "none",
      "experience_years": 15,
      "programming_languages": [
        "Lua C++"
      ]
    },
    {
      "participant_id": "P100",
      "age": 19,
      "gender": "male",
      "handedness": "unknown",
      "vision": "none",
      "experience_years": 1,
      "programming_languages": [
        "Java C"
      ]
    },
    {
      "participant_id": "P101",
      "age": 46,
      "gender": "male",
      "handedness": "unknown",
      "vision": "glasses",
      "experience_years": 36,
      "programming_languages": [
        "C C++"
      ]
    },
    {
      "participant_id": "P102",
      "age": 30,
      "gender": "male",
      "handedness": "unknown",
      "vision": "glasses",
      "experience_years": 8,
      "programming_languages": [
        "python"
      ]
    },
    {
      "participant_id": "P103",
      "age": 23,
      "gender": "female",
      "handedness": "unknown",
      "vision": "none",
      "experience_years": 1,
      "programming_languages": [
        "HTML"
      ]
    },
    {
      "participant_id": "P104",
      "age": 24,
      "gender": "female",
      "handedness": "unknown",
      "vision": "glasses",
      "experience_years": 3,
      "programming_languages": [
        "C/C++",
        "HTML",
        "CSS PHP",
        "Javascript",
        "C#"
      ]
    },
    {
      "participant_id": "P105",
      "age": 20,
      "gender": "male",
      "handedness": "unknown",
      "vision": "none",
      "experience_years": 4,
      "programming_languages": [
        "C# Python Javascript Java PHP"
      ]
    },
    {
      "participant_id": "P106",
      "age": 32,
      "gender": "male",
      "handedness": "unknown",
      "vision": "glasses",
      "experience_years": 10,
      "programming_languages": [
        "c++ matlab"
      ]
    },
    {
      "participant_id": "P107",
      "age": 48,
      "gender": "female",
      "handedness": "unknown",
      "vision": "glasses",
      "experience_years": 3,
      "programming_languages": [
        "Pearl",
        "HTML"
      ]
    },
    {
      "participant_id": "P108",
      "age": 22,
      "gender": "male",
      "handedness": "unknown",
      "vision": "glasses",
      "experience_years": 4,
      "programming_languages": [
        "C",
        "C++",
        "C#",
        "Perl",
        "Python",
        "VB.net",
        "LISP"
      ]
    },
    {
      "participant_id": "P109",
      "age": 20,
      "gender": "male",
      "handedness": "unknown",
      "vision": "none",
      "experience_years": 10,
      "programming_languages": [
        "C C++ Java PHP"
      ]
    },
    {
      "participant_id": "P110",
      "age": 20,
      "gender": "male",
      "handedness": "unknown",
      "vision": "none",
      "experience_years": 0,
      "programming_languages": [
        "C medium"
      ]
    },
    {
      "participant_id": "P111",
      "age": 21,
      "gender": "male",
      "handedness": "unknown",
      "vision": "none",
      "experience_years": 1,
      "programming_languages": [
        "C++",
        "C",
        "Java"
      ]
    },
    {
      "participant_id": "P112",
      "age": 21,
      "gender": "male",
      "handedness": "unknown",
      "vision": "glasses",
      "experience_years": 7,
      "programming_languages": [
        "low"
      ]
    },
    {
      "participant_id": "P113",
      "age": 36,
      "gender": "male",
      "handedness": "unknown",
      "vision": "glasses",
      "experience_years": 10,
      "programming_languages": [
        "Java",
        "Ruby",
        "C++",
        "Python",
        "Scala"
      ]
    },
    {
      "participant_id": "P114",
      "age": 25,
      "gender": "male",
      "handedness": "unknown",
      "vision": "glasses",
      "experience_years": 5,
      "programming_languages": [
        "C",
        "R",
        "Python"
      ]
    },
    {
      "participant_id": "P115",
      "age": 24,
      "gender": "male",
      "handedness": "unknown",
      "vision": "none",
      "experience_years": 5,
      "programming_languages": [
        "C++ Lua"
      ]
    },
    {
      "participant_id": "P116",
      "age": 20,
      "gender": "male",
      "handedness": "unknown",
      "vision": "none",
      "experience_years": 0,
      "programming_languages": [
        "C low"
      ]
    },
    {
      "participant_id": "P117",
      "age": 38,
      "gender": "male",
      "handedness": "unknown",
      "vision": "none",
      "experience_years": 20,
      "programming_languages": [
        "C++ Matlab Python Java Javascript LISP Prolog Modula-2"
      ]
    },
    {
      "participant_id": "P118",
      "age": 23,
      "gender": "male",
      "handedness": "unknown",
      "vision": "none",
      "experience_years": 6,
      "programming_languages": [
        "Ruby high JavaScript medium"
      ]
    },
    {
      "participant_id": "P119",
      "age": 46,
      "gender": "male",
      "handedness": "unknown",
      "vision": "contact_lenses",
      "experience_years": 0,
      "programming_languages": []
    },
    {
      "participant_id": "P120",
      "age": 27,
      "gender": "male",
      "handedness": "unknown",
      "vision": "glasses",
      "experience_years": 4,
      "programming_languages": [
        "C Javascript"
      ]
    },
    {
      "participant_id": "P121",
      "age": 38,
      "gender": "female",
      "handedness": "unknown",
      "vision": "glasses",
      "experience_years": 10,
      "programming_languages": [
        "C++ Java Python"
      ]
    },
    {
      "participant_id": "P122",
      "age": 27,
      "gender": "male",
      "handedness": "unknown",
      "vision": "none",
      "experience_years": 6,
      "programming_languages": [
        "C medium C++ medium Java low PHP low"
      ]
    },
    {
      "participant_id": "P123",
      "age": 62,
      "gender": "male",
      "handedness": "unknown",
      "vision": "glasses",
      "experience_years": 40,
      "programming_languages": [
        "Pascal",
        "Javascript",
        "Scala",
        "C",
        "C++",
        "C#",
        "Closure",
        "..."
      ]
    },
    {
      "participant_id": "P124",
      "age": 22,
      "gender": "male",
      "handedness": "unknown",
      "vision": "none",
      "experience_years": 5,
      "programming_languages": [
        "C#",
        "Python",
        "JavaScript"
      ]
    },
    {
      "participant_id": "P125",
      "age": 27,
      "gender": "male",
      "handedness": "unknown",
      "vision": "glasses",
      "experience_years": 2,
      "programming_languages": [
        "Java C"
      ]
    },
    {
      "participant_id": "P126",
      "age": 24,
      "gender": "male",
      "handedness": "unknown",
      "vision": "none",
      "experience_years": 15,
      "programming_languages": [
        "PHP C# ruby",
        "python"
      ]
    },
    {
      "participant_id": "P127",
      "age": 23,
      "gender": "male",
      "handedness": "unknown",
      "vision": "glasses",
      "experience_years": 2,
      "programming_languages": [
        "c++ python php javascript BASIC"
      ]
    },
    {
      "participant_id": "P128",
      "age": 33,
      "gender": "male",
      "handedness": "unknown",
      "vision": "none",
      "experience_years": 18,
      "programming_languages": [
        "c++ java python pascal basic"
      ]
    },
    {
      "participant_id": "P129",
      "age": 26,
      "gender": "male",
      "handedness": "unknown",
      "vision": "glasses",
      "experience_years": 7,
      "programming_languages": [
        "C C++ MATLAB VHDL verilog Python C#"
      ]
    },
    {
      "participant_id": "P130",
      "age": 22,
      "gender": "male",
      "handedness": "unknown",
      "vision": "glasses",
      "experience_years": 0,
      "programming_languages": [
        "Java Scirpt - low"
      ]
    },
    {
      "participant_id": "P131",
      "age": 21,
      "gender": "male",
      "handedness": "unknown",
      "vision": "none",
      "experience_years": 1,
      "programming_languages": [
        "Javascript",
        "PHP",
        "C"
      ]
    },
    {
      "participant_id": "P132",
      "age": 22,
      "gender": "male",
      "handedness": "unknown",
      "vision": "glasses",
      "experience_years": 1,
      "programming_languages": [
        "Java"
      ]
    },
    {
      "participant_id": "P133",
      "age": 24,
      "gender": "male",
      "handedness": "unknown",
      "vision": "glasses",
      "experience_years": 5,
      "programming_languages": [
        "Python",
        "Java",
        "C++",
        "Lua"
      ]
    },
    {
      "participant_id": "P134",
      "age": 27,
      "gender": "male",
      "handedness": "unknown",
      "vision": "none",
      "experience_years": 1,
      "programming_languages": [
        "c# c"
      ]
    },
    {
      "participant_id": "P135",
      "age": 25,
      "gender": "male",
      "handedness": "unknown",
      "vision": "contact_lenses",
      "experience_years": 3,
      "programming_languages": [
        "Java",
        "Python",
        "Embedded C"
      ]
    },
    {
      "participant_id": "P136",
      "age": 55,
      "gender": "male",
      "handedness": "unknown",
      "vision": "none",
      "experience_years": 35,
      "programming_languages": [
        "Perl medium Pascal high c++ high java medium python low"
      ]
    },
    {
      "participant_id": "P137",
      "age": 21,
      "gender": "male",
      "handedness": "unknown",
      "vision": "glasses",
      "experience_years": 6,
      "programming_languages": [
        "C",
        "C++",
        "Java",
        "Javascript",
        "PHP",
        "Python"
      ]
    },
    {
      "participant_id": "P138",
      "age": 25,
      "gender": "male",
      "handedness": "unknown",
      "vision": "none",
      "experience_years": 6,
      "programming_languages": [
        "ruby R"
      ]
    },
    {
      "participant_id": "P139",
      "age": 19,
      "gender": "female",
      "handedness": "unknown",
      "vision": "none",
      "experience_years": 0,
      "programming_languages": [
        "Java - low"
      ]
    },
    {
      "participant_id": "P140",
      "age": 27,
      "gender": "male",
      "handedness": "unknown",
      "vision": "none",
      "experience_years": 7,
      "programming_languages": [
        "C++ python haskell"
      ]
    },
    {
      "participant_id": "P141",
      "age": 31,
      "gender": "female",
      "handedness": "unknown",
      "vision": "contact_lenses",
      "experience_years": 2,
      "programming_languages": [
        "Matlab Python"
      ]
    },
    {
      "participant_id": "P142",
      "age": 25,
      "gender": "male",
      "handedness": "unknown",
      "vision": "none",
      "experience_years": 3,
      "programming_languages": [
        "C-medium",
        "C#-low",
        "Java-medium",
        "JS-low"
      ]
    },
    {
      "participant_id": "P143",
      "age": 26,
      "gender": "male",
      "handedness": "unknown",
      "vision": "none",
      "experience_years": 16,
      "programming_languages": [
        "C/C++",
        "JavaScript",
        "Python",
        "C#"
      ]
    },
    {
      "participant_id": "P144",
      "age": 20,
      "gender": "female",
      "handedness": "unknown",
      "vision": "contact_lenses",
      "experience_years": 2,
      "programming_languages": [
        "Python Javascript C/C++"
      ]
    },
    {
      "participant_id": "P145",
      "age": 23,
      "gender": "female",
      "handedness": "unknown",
      "vision": "glasses",
      "experience_years": 5,
      "programming_languages": [
        "C C# Java  php xml html matlab ActionScript3",
        "assembly"
      ]
    },
    {
      "participant_id": "P146",
      "age": 19,
      "gender": "female",
      "handedness": "unknown",
      "vision": "glasses",
      "experience_years": 0,
      "programming_languages": [
        "None at all. Level of expertise is low."
      ]
    },
    {
      "participant_id": "P147",
      "age": 21,
      "gender": "male",
      "handedness": "unknown",
      "vision": "none",
      "experience_years": 2,
      "programming_languages": [
        "C",
        "Pythom"
      ]
    },
    {
      "participant_id": "P148",
      "age": 26,
      "gender": "female",
      "handedness": "unknown",
      "vision": "glasses",
      "experience_years": 2,
      "programming_languages": [
        "c# jAVA ASP .NET Python C Java script SQL"
      ]
    },
    {
      "participant_id": "P149",
      "age": 40,
      "gender": "female",
      "handedness": "unknown",
      "vision": "contact_lenses",
      "experience_years": 15,
      "programming_languages": [
        "C/ C++ high",
        "MATLAB high",
        "JAVA medium",
        "Python low"
      ]
    },
    {
      "participant_id": "P150",
      "age": 47,
      "gender": "female",
      "handedness": "unknown",
      "vision": "none",
      "experience_years": 10,
      "programming_languages": [
        "Python C C++ PHP JavaScript"
      ]
    },
    {
      "participant_id": "P151",
      "age": 44,
      "gender": "male",
      "handedness": "unknown",
      "vision": "none",
      "experience_years": 15,
      "programming_languages": [
        "c++ high Python medium Lisp medium Prolog medium"
      ]
    },
    {
      "participant_id": "P152",
      "age": 20,
      "gender": "female",
      "handedness": "unknown",
      "vision": "none",
      "experience_years": 5,
      "programming_languages": [
        "Phascal C"
      ]
    },
    {
      "participant_id": "P153",
      "age": 26,
      "gender": "male",
      "handedness": "unknown",
      "vision": "none",
      "experience_years": 3,
      "programming_languages": [
        "C# c++ c  assembly"
      ]
    },
    {
      "participant_id": "P154",
      "age": 24,
      "gender": "male",
      "handedness": "unknown",
      "vision": "none",
      "experience_years": 2,
      "programming_languages": [
        "C medium"
      ]
    },
    {
      "participant_id": "P155",
      "age": 21,
      "gender": "male",
      "handedness": "unknown",
      "vision": "contact_lenses",
      "experience_years": 3,
      "programming_languages": [
        "C Ruby Java"
      ]
    },
    {
      "participant_id": "P156",
      "age": 21,
      "gender": "male",
      "handedness": "unknown",
      "vision": "none",
      "experience_years": 7,
      "programming_languages": [
        "c",
        "php",
        "java"
      ]
    },
    {
      "participant_id": "P157",
      "age": 23,
      "gender": "male",
      "handedness": "unknown",
      "vision": "none",
      "experience_years": 2,
      "programming_languages": [
        "C C++"
      ]
    },
    {
      "participant_id": "P158",
      "age": 40,
      "gender": "male",
      "handedness": "unknown",
      "vision": "glasses",
      "experience_years": 20,
      "programming_languages": [
        "C#"
      ]
    },
    {
      "participant_id": "P159",
      "age": 24,
      "gender": "male",
      "handedness": "unknown",
      "vision": "glasses",
      "experience_years": 5,
      "programming_languages": [
        "c# c c++"
      ]
    },
    {
      "participant_id": "P160",
      "age": 27,
      "gender": "male",
      "handedness": "unknown",
      "vision": "none",
      "experience_years": 3,
      "programming_languages": [
        "javascript"
      ]
    },
    {
      "participant_id": "P161",
      "age": 20,
      "gender": "male",
      "handedness": "unknown",
      "vision": "none",
      "experience_years": 8,
      "programming_languages": [
        "Java",
        "Python",
        "C++",
        "Javascript"
      ]
    },
    {
      "participant_id": "P162",
      "age": 25,
      "gender": "male",
      "handedness": "unknown",
      "vision": "none",
      "experience_years": 2,
      "programming_languages": [
        "C++"
      ]
    },
    {
      "participant_id": "P163",
      "age": 17,
      "gender": "female",
      "handedness": "unknown",
      "vision": "glasses",
      "experience_years": 3,
      "programming_languages": [
        "LabView",
        "C"
      ]
    },
    {
      "participant_id": "P164",
      "age": 18,
      "gender": "male",
      "handedness": "unknown",
      "vision": "none",
      "experience_years": 3,
      "programming_languages": [
        "C#"
      ]
    },
    {
      "participant_id": "P165",
      "age": 25,
      "gender": "male",
      "handedness": "unknown",
      "vision": "none",
      "experience_years": 1,
      "programming_languages": [
        "C C#"
      ]
    },
    {
      "participant_id": "P166",
      "age": 21,
      "gender": "male",
      "handedness": "unknown",
      "vision": "none",
      "experience_years": 4,
      "programming_languages": [
        "PHP high",
        "javascript high",
        "Java medium",
        "C# medium",
        "C Low"
      ]
    },
    {
      "participant_id": "P167",
      "age": 49,
      "gender": "male",
      "handedness": "unknown",
      "vision": "none",
      "experience_years": 0,
      "programming_languages": []
    },
    {
      "participant_id": "P168",
      "age": 20,
      "gender": "male",
      "handedness": "unknown",
      "vision": "glasses",
      "experience_years": 1,
      "programming_languages": [
        "C",
        "Python"
      ]
    },
    {
      "participant_id": "P169",
      "age": 27,
      "gender": "male",
      "handedness": "unknown",
      "vision": "contact_lenses",
      "experience_years": 1,
      "programming_languages": [
        "C  low",
        "C++ low",
        "SQL low"
      ]
    },
    {
      "participant_id": "P170",
      "age": 59,
      "gender": "male",
      "handedness": "unknown",
      "vision": "none",
      "experience_years": 35,
      "programming_languages": [
        "Python low C++ low ELAN high Algol low Fortran low Java low Basic low"
      ]
    },
    {
      "participant_id": "P171",
      "age": 20,
      "gender": "male",
      "handedness": "unknown",
      "vision": "none",
      "experience_years": 4,
      "programming_languages": [
        "C"
      ]
    },
    {
      "participant_id": "P172",
      "age": 22,
      "gender": "male",
      "handedness": "unknown",
      "vision": "none",
      "experience_years": 2,
      "programming_languages": [
        "c",
        "c#",
        "java",
        "c++",
        "assembly"
      ]
    },
    {
      "participant_id": "P173",
      "age": 28,
      "gender": "female",
      "handedness": "unknown",
      "vision": "contact_lenses",
      "experience_years": 5,
      "programming_languages": [
        "C"
      ]
    },
    {
      "participant_id": "P174",
      "age": 21,
      "gender": "female",
      "handedness": "unknown",
      "vision": "glasses",
      "experience_years": 1,
      "programming_languages": [
        "C#",
        "C",
        "PHP"
      ]
    },
    {
      "participant_id": "P175",
      "age": 19,
      "gender": "male",
      "handedness": "unknown",
      "vision": "glasses",
      "experience_years": 4,
      "programming_languages": [
        "Python",
        "C#",
        "Scala",
        "Java"
      ]
    },
    {
      "participant_id": "P176",
      "age": 36,
      "gender": "female",
      "handedness": "unknown",
      "vision": "none",
      "experience_years": 3,
      "programming_languages": [
        "C"
      ]
    },
    {
      "participant_id": "P177",
      "age": 25,
      "gender": "male",
      "handedness": "unknown",
      "vision": "none",
      "experience_years": 2,
      "programming_languages": [
        "C# C unix"
      ]
    },
    {
      "participant_id": "P178",
      "age": 21,
      "gender": "male",
      "handedness": "unknown",
      "vision": "none",
      "experience_years": 5,
      "programming_languages": [
        "Ruby",
        "C#"
      ]
    },
    {
      "participant_id": "P179",
      "age": 19,
      "gender": "male",
      "handedness": "unknown",
      "vision": "glasses",
      "experience_years": 0,
      "programming_languages": []
    },
    {
      "participant_id": "P180",
      "age": 22,
      "gender": "female",
      "handedness": "unknown",
      "vision": "none",
      "experience_years": 2,
      "programming_languages": [
        "c++ low"
      ]
    },
    {
      "participant_id": "P181",
      "age": 32,
      "gender": "female",
      "handedness": "unknown",
      "vision": "none",
      "experience_years": 0,
      "programming_languages": []
    },
    {
      "participant_id": "P182",
      "age": 20,
      "gender": "male",
      "handedness": "unknown",
      "vision": "glasses",
      "experience_years": 1,
      "programming_languages": [
        "C#",
        "Visual Basic",
        "HTML"
      ]
    },
    {
      "participant_id": "P183",
      "age": 26,
      "gender": "male",
      "handedness": "unknown",
      "vision": "contact_lenses",
      "experience_years": 2,
      "programming_languages": [
        "python",
        "c#"
      ]
    },
    {
      "participant_id": "P184",
      "age": 20,
      "gender": "male",
      "handedness": "unknown",
      "vision": "glasses",
      "experience_years": 3,
      "programming_languages": [
        "C C++"
      ]
    },
    {
      "participant_id": "P185",
      "age": 27,
      "gender": "male",
      "handedness": "unknown",
      "vision": "none",
      "experience_years": 4,
      "programming_languages": [
        "Python",
        "JavaScript"
      ]
    },
    {
      "participant_id": "P186",
      "age": 22,
      "gender": "female",
      "handedness": "unknown",
      "vision": "glasses",
      "experience_years": 3,
      "programming_languages": [
        "c",
        "java",
        "assembly"
      ]
    },
    {
      "participant_id": "P187",
      "age": 22,
      "gender": "female",
      "handedness": "unknown",
      "vision": "glasses",
      "experience_years": 2,
      "programming_languages": [
        "Java",
        "Arduino"
      ]
    },
    {
      "participant_id": "P188",
      "age": 22,
      "gender": "male",
      "handedness": "unknown",
      "vision": "none",
      "experience_years": 1,
      "programming_languages": [
        "Scala",
        "Python"
      ]
    },
    {
      "participant_id": "P189",
      "age": 24,
      "gender": "male",
      "handedness": "unknown",
      "vision": "none",
      "experience_years": 5,
      "programming_languages": [
        "c-medium c++-low python-medium html-high"
      ]
    },
    {
      "participant_id": "P190",
      "age": 26,
      "gender": "male",
      "handedness": "unknown",
      "vision": "none",
      "experience_years": 8,
      "programming_languages": [
        "PHP C# Ruby"
      ]
    },
    {
      "participant_id": "P191",
      "age": 24,
      "gender": "male",
      "handedness": "unknown",
      "vision": "contact_lenses",
      "experience_years": 3,
      "programming_languages": [
        "c#(medium("
      ]
    },
    {
      "participant_id": "P192",
      "age": 26,
      "gender": "male",
      "handedness": "unknown",
      "vision": "none",
      "experience_years": 5,
      "programming_languages": [
        "C C++ Javascript Python"
      ]
    },
    {
      "participant_id": "P193",
      "age": 31,
      "gender": "male",
      "handedness": "unknown",
      "vision": "glasses",
      "experience_years": 3,
      "programming_languages": [
        "C",
        "Ruby",
        "XML"
      ]
    },
    {
      "participant_id": "P194",
      "age": 24,
      "gender": "male",
      "handedness": "unknown",
      "vision": "glasses",
      "experience_years": 2,
      "programming_languages": [
        "Java",
        "C",
        "C++",
        "HTML",
        "CSS",
        "javascript",
        "LISP"
      ]
    },
    {
      "participant_id": "P195",
      "age": 49,
      "gender": "male",
      "handedness": "unknown",
      "vision": "glasses",
      "experience_years": 20,
      "programming_languages": [
        "C++ Python C JavaScript VisualBasic C#"
      ]
    },
    {
      "participant_id": "P196",
      "age": 25,
      "gender": "male",
      "handedness": "unknown",
      "vision": "none",
      "experience_years": 1,
      "programming_languages": [
        "javascript",
        "c"
      ]
    },
    {
      "participant_id": "P197",
      "age": 32,
      "gender": "male",
      "handedness": "unknown",
      "vision": "glasses",
      "experience_years": 2,
      "programming_languages": [
        "C++ low Java medium Swift low Javascript low"
      ]
    },
    {
      "participant_id": "P198",
      "age": 22,
      "gender": "male",
      "handedness": "unknown",
      "vision": "none",
      "experience_years": 3,
      "programming_languages": [
        "C/C++ javascript HTML SQL"
      ]
    },
    {
      "participant_id": "P199",
      "age": 28,
      "gender": "male",
      "handedness": "unknown",
      "vision": "none",
      "experience_years": 1,
      "programming_languages": [
        "java-medium c-medium"
      ]
    },
    {
      "participant_id": "P200",
      "age": 19,
      "gender": "male",
      "handedness": "unknown",
      "vision": "none",
      "experience_years": 1,
      "programming_languages": [
        "Java C"
      ]
    },
    {
      "participant_id": "P201",
      "age": 36,
      "gender": "male",
      "handedness": "unknown",
      "vision": "glasses",
      "experience_years": 10,
      "programming_languages": [
        "Matlab C/C++"
      ]
    },
    {
      "participant_id": "P202",
      "age": 22,
      "gender": "male",
      "handedness": "unknown",
      "vision": "contact_lenses",
      "experience_years": 4,
      "programming_languages": [
        "C C++ html css"
      ]
    },
    {
      "participant_id": "P203",
      "age": 21,
      "gender": "male",
      "handedness": "unknown",
      "vision": "glasses",
      "experience_years": 2,
      "programming_languages": [
        "Javascript C C++ Python"
      ]
    },
    {
      "participant_id": "P204",
      "age": 20,
      "gender": "female",
      "handedness": "unknown",
      "vision": "glasses",
      "experience_years": 0,
      "programming_languages": [
        "N/A"
      ]
    },
    {
      "participant_id": "P205",
      "age": 48,
      "gender": "male",
      "handedness": "unknown",
      "vision": "none",
      "experience_years": 15,
      "programming_languages": [
        "python",
        "c",
        "java",
        "assembly"
      ]
    },
    {
      "participant_id": "P206",
      "age": 30,
      "gender": "male",
      "handedness": "unknown",
      "vision": "none",
      "experience_years": 1,
      "programming_languages": [
        "java Script"
      ]
    },
    {
      "participant_id": "P207",
      "age": 20,
      "gender": "female",
      "handedness": "unknown",
      "vision": "contact_lenses",
      "experience_years": 2,
      "programming_languages": [
        "C Python"
      ]
    },
    {
      "participant_id": "P208",
      "age": 24,
      "gender": "male",
      "handedness": "unknown",
      "vision": "none",
      "experience_years": 2,
      "programming_languages": [
        "C# LOW",
        "C LOW",
        "JAVA MEDIUM",
        "PYTHON LOW"
      ]
    },
    {
      "participant_id": "P209",
      "age": 78,
      "gender": "female",
      "handedness": "unknown",
      "vision": "contact_lenses",
      "experience_years": 56,
      "programming_languages": [
        "Algol",
        "PL1",
        "Fortran",
        "C",
        "Snobol Lisp",
        "APL"
      ]
    },
    {
      "participant_id": "P210",
      "age": 31,
      "gender": "male",
      "handedness": "unknown",
      "vision": "none",
      "experience_years": 18,
      "programming_languages": [
        "C C#"
      ]
    },
    {
      "participant_id": "P211",
      "age": 21,
      "gender": "female",
      "handedness": "unknown",
      "vision": "none",
      "experience_years": 1,
      "programming_languages": [
        "C",
        "medium"
      ]
    },
    {
      "participant_id": "P212",
      "age": 21,
      "gender": "male",
      "handedness": "unknown",
      "vision": "glasses",
      "experience_years": 3,
      "programming_languages": [
        "C",
        "C++"
      ]
    },
    {
      "participant_id": "P213",
      "age": 26,
      "gender": "male",
      "handedness": "unknown",
      "vision": "none",
      "experience_years": 3,
      "programming_languages": [
        "Python VBA Excel C"
      ]
    },
    {
      "participant_id": "P214",
      "age": 21,
      "gender": "male",
      "handedness": "unknown",
      "vision": "none",
      "experience_years": 4,
      "programming_languages": [
        "C",
        "JavaScript"
      ]
    },
    {
      "participant_id": "P215",
      "age": 22,
      "gender": "male",
      "handedness": "unknown",
      "vision": "none",
      "experience_years": 2,
      "programming_languages": [
        "C c# Java"
      ]
    },
    {
      "participant_id": "P216",
      "age": 22,
      "gender": "female",
      "handedness": "unknown",
      "vision": "glasses",
      "experience_years": 0,
      "programming_languages": [
        "Low"
      ]
    }
  ],
  "inclusion_criteria": "Adults who completed the EMIP code comprehension tasks."
}